{
    "1": [
        {
            "title": "Kung Fu",
            "time": "4:00pm - 5:00pm",
            "location": "@Fishers Elementary - FES Playground"
        }
    ],
    "2": [
        {
            "title": "Kindergarten Parent Night",
            "time": "6:30pm - 7:30pm",
            "location": "Room 112, Room 114, Room 115, Room 116"
        }
    ],
    "3": [
        {
            "title": "HSE Before The Bell",
            "time": "5:30pm - 7:30pm",
            "location": "@Nickel Plate District Amphitheater"
        }
    ],
    "7": [
        {
            "title": "FES Open House",
            "time": "4:00pm - 6:00pm",
            "location": "@Fishers Elementary - FES Cafeteria"
        }
    ],
    "16": [
        {
            "title": "Meet The Teacher Night 3rd & 4th",
            "time": "5:15pm - 6:15pm",
            "location": null
        },
        {
            "title": "Meet The Teacher Night 1st,2nd & FAP",
            "time": "6:30pm - 7:30pm",
            "location": null
        }
    ],
    "23": [
        {
            "title": "2nd Grade Field Trip",
            "time": "9:30am - 1:30pm",
            "location": "@Fishers Elementary - FES Parking Lot - Front"
        },
        {
            "title": "2nd Grade Field Trip",
            "time": "9:30am - 1:30pm",
            "location": "@Fishers Elementary - FES Parking Lot - Front"
        }
    ],
    "24": [
        {
            "title": "2nd Grade Field Trip",
            "time": "9:30am - 1:30pm",
            "location": "@Fishers Elementary - FES Parking Lot - Front"
        },
        {
            "title": "Boy Scout Recruitment Night",
            "time": "6:30pm - 8:00pm",
            "location": "Cumberland Road Elementary - CRE CAFETERIA, Fishers Elementary - FES Cafeteria, New Britton Elementary - NBE Cafeteria, Thorpe Creek Elementary - TCE Gym, Sand Creek Intermediate - SCI GYM, Hamilton Southeastern Junior High/Intermediate - HJH Auditeria Panther Hall, Riverside - RSI GYM, Brooks School Elementary - BSE Cafeteria, Hoosier Road Elementary - HRE Cafeteria, Deer Creek Elementary  - DCE Cafeteria, Sand Creek Elementary - SCE Cafeteria, Fall Creek Elementary - FCE Cafeteria, Harrison Parkway Elementary - HPE Cafeteria, Fall Creek Intermediate - FCI Cafeteria, Lantern Road Elementary - Picnic Shelter, Geist Elementary - GES Cafeteria, Southeastern Elementary School - SES Cafeteria, Geist Elementary - GES Gym, Brooks School Elementary - BSE Gym"
        }
    ],
    "25": [
        {
            "title": "2nd Grade Field Trip",
            "time": "9:30am - 1:30pm",
            "location": "@Fishers Elementary - FES Parking Lot - Front"
        },
        {
            "title": "FES School-Wide BBQ",
            "time": "5:30pm - 8:00pm",
            "location": "@Entire Building - Fishers Elementary"
        }
    ],
    "30": [
        {
            "title": "Cub Scout Den Meetings Pack 109 FES",
            "time": "6:15pm - 8:15pm",
            "location": "Fishers Elementary - FES Cafeteria, Fishers Elementary - FES Gym"
        }
    ],
    "31": [
        {
            "title": "Fall Picture Day",
            "time": "7:30am - 2:00pm",
            "location": "@Fishers Elementary - FES Media Center"
        },
        {
            "title": "School Picture Day",
            "time": "8:00pm - 1:00pm",
            "location": "@Fishers Elementary - FES Media Center"
        }
    ]
}